{
  "rule_name": "APT_Sauron_extras.yar",
  "rule_type": "yara",
  "source": "MISP",
  "event_id": 0,
  "event_uuid": "github:Yara-Rules/rules@0f93570194a8",
  "content_hash": "d8037689b0677aff62d0978817cc8bbbf2bcd9f6e742b8509b7e1139cc98238f",
  "validation_status": "passed",
  "validation_errors": [],
  "validation_warnings": [],
  "conversion_status": "none",
  "conversion_target": null,
  "tags": [
    "source:github",
    "repo:Yara-Rules/rules",
    "external",
    "unverified"
  ],
  "deployment_status": "pending",
  "timestamp": "2026-07-03T05:08:31.442669+00:00"
}