{
  "rule_name": "APT_RedLeaves.yar",
  "rule_type": "yara",
  "source": "MISP",
  "event_id": 0,
  "event_uuid": "github:Yara-Rules/rules@0f93570194a8",
  "content_hash": "0ea21d9d3aef337a629760bed50c2f8ec465c735170b135b73de33a1a394ceb9",
  "validation_status": "passed",
  "validation_errors": [],
  "validation_warnings": [],
  "conversion_status": "none",
  "conversion_target": null,
  "tags": [
    "source:github",
    "repo:Yara-Rules/rules",
    "external",
    "unverified"
  ],
  "deployment_status": "pending",
  "timestamp": "2026-07-03T05:08:31.467329+00:00"
}