{
  "rule_name": "MALW_hancitor.yar",
  "rule_type": "yara",
  "source": "MISP",
  "event_id": 0,
  "event_uuid": "github:Yara-Rules/rules@0f93570194a8",
  "content_hash": "a2425da002ecf13675e4f7061db20950ebfba09b2eb0849949f1b4240f3874c0",
  "validation_status": "passed",
  "validation_errors": [],
  "validation_warnings": [],
  "conversion_status": "none",
  "conversion_target": null,
  "tags": [
    "source:github",
    "repo:Yara-Rules/rules",
    "external",
    "unverified"
  ],
  "deployment_status": "pending",
  "timestamp": "2026-07-03T05:08:30.324554+00:00"
}