{
  "rule_name": "proc_creation_win_sc_disable_service.yml",
  "rule_type": "sigma",
  "source": "MISP",
  "event_id": 0,
  "event_uuid": "github:SigmaHQ/sigma@941c27449146",
  "content_hash": "ce81f2df4d65941e8bf58785e75ad5cbd55207df600f52650b7747b4f6bd3c38",
  "validation_status": "passed",
  "validation_errors": [],
  "validation_warnings": [
    "Parsing Sigma rules",
    "Checking Sigma rules"
  ],
  "conversion_status": "converted",
  "conversion_target": "wazuh",
  "tags": [
    "source:github",
    "repo:SigmaHQ/sigma",
    "external",
    "unverified"
  ],
  "deployment_status": "pending",
  "timestamp": "2026-07-03T05:03:52.097448+00:00"
}