{
  "rule_name": "proc_creation_win_certutil_ntlm_coercion.yml",
  "rule_type": "sigma",
  "source": "MISP",
  "event_id": 0,
  "event_uuid": "github:SigmaHQ/sigma@941c27449146",
  "content_hash": "01ef9a41e0b14e8fc8f45bed1ea30e57be09ee7e0e71a5caee4d73f642c47b36",
  "validation_status": "passed",
  "validation_errors": [],
  "validation_warnings": [
    "Parsing Sigma rules",
    "Checking Sigma rules"
  ],
  "conversion_status": "converted",
  "conversion_target": "wazuh",
  "tags": [
    "source:github",
    "repo:SigmaHQ/sigma",
    "external",
    "unverified"
  ],
  "deployment_status": "pending",
  "timestamp": "2026-07-03T05:08:07.508808+00:00"
}