{
  "rule_name": "proc_creation_win_office_arbitrary_cli_download.yml",
  "rule_type": "sigma",
  "source": "MISP",
  "event_id": 0,
  "event_uuid": "github:SigmaHQ/sigma@941c27449146",
  "content_hash": "efd34e04e50659d15da1ed494331ff1d1b2f75893576c7bd3105427a2dfafe39",
  "validation_status": "passed",
  "validation_errors": [],
  "validation_warnings": [
    "Parsing Sigma rules",
    "Checking Sigma rules"
  ],
  "conversion_status": "converted",
  "conversion_target": "wazuh",
  "tags": [
    "source:github",
    "repo:SigmaHQ/sigma",
    "external",
    "unverified"
  ],
  "deployment_status": "pending",
  "timestamp": "2026-07-03T05:05:47.372052+00:00"
}